baml_core_ffi-0.1.7.dist-info/METADATA
baml_core_ffi-0.1.7.dist-info/WHEEL
baml_core_ffi-0.1.7.dist-info/license_files/LICENSE
baml_core_ffi/__init__.py
baml_core_ffi/__init__.pyi
baml_core_ffi/py.typed
baml_core_ffi/baml_core_ffi.abi3.so
baml_core_ffi-0.1.7.dist-info/RECORD
