Metadata-Version: 2.3
Name: baml_core_ffi
Version: 0.1.7
License-File: LICENSE
Summary: BAML python bindings (pyproject.toml)
Author: Boundary <contact@boundaryml.com>
Author-email: Boundary <contact@boundaryml.com>
